{
  "$id": "format_version",
  "title": "Format Version",
  "description": "A version that tells minecraft what type of data format can be expected when reading this file.",
  "pattern": "^([1-9]+)\\.([0-9]+)\\.([0-9]+)$",
  "type": "string",
  "default": "1.20.41",
  "examples": ["1.20.41", "1.19.0", "1.18.0", "1.17.0", "1.16.0", "1.15.0", "1.14.0", "1.13.0", "1.12.0", "1.10.0", "1.8.0"],
  "defaultSnippets": [{ "label": "New Format version", "body": "1.${1|8,10,12,17,18,19,20|}.${3|2|0|}" }]
}
